py3_wisharetec/__init__.py
py3_wisharetec/scaasp/__init__.py
py3_wisharetec/scaasp/admin.py
py3_wisharetec-1.1.5.dist-info/licenses/LICENSE
py3_wisharetec-1.1.5.dist-info/METADATA
py3_wisharetec-1.1.5.dist-info/WHEEL
py3_wisharetec-1.1.5.dist-info/top_level.txt
py3_wisharetec-1.1.5.dist-info/RECORD
