Metadata-Version: 2.4
Name: py3-wisharetec
Version: 1.1.5
Summary: The Python3 Wisharetec Library Developed By Guolei
Home-page: https://github.com/guolei19850528/py3_wisharetec
Author: guolei
Author-email: 174000902@qq.com
License: MIT
Requires-Python: >=3.0
License-File: LICENSE
Requires-Dist: py3-requests
Requires-Dist: addict
Requires-Dist: retrying
Requires-Dist: jsonschema
Requires-Dist: diskcache
Requires-Dist: redis
Requires-Dist: setuptools
Requires-Dist: wheel
Dynamic: author
Dynamic: author-email
Dynamic: description
Dynamic: description-content-type
Dynamic: home-page
Dynamic: license
Dynamic: license-file
Dynamic: requires-dist
Dynamic: requires-python
Dynamic: summary
